{"trial_id": "13", "hyperparameters": {"space": [{"class_name": "Choice", "config": {"name": "units_input", "default": 32, "conditions": [], "values": [32, 64, 128], "ordered": true}}, {"class_name": "Boolean", "config": {"name": "use_hidden_layer", "default": false, "conditions": []}}, {"class_name": "Choice", "config": {"name": "learning_rate", "default": 0.01, "conditions": [], "values": [0.01, 0.001, 0.0001], "ordered": true}}, {"class_name": "Choice", "config": {"name": "units_hidden", "default": 32, "conditions": [], "values": [32, 64, 128], "ordered": true}}], "values": {"units_input": 128, "use_hidden_layer": true, "learning_rate": 0.001, "units_hidden": 128}}, "metrics": {"metrics": {"accuracy": {"direction": "max", "observations": [{"value": [0.8435852527618408], "step": 19}]}, "loss": {"direction": "min", "observations": [{"value": [0.36577171087265015], "step": 19}]}, "val_accuracy": {"direction": "max", "observations": [{"value": [0.8461538553237915], "step": 19}]}, "val_loss": {"direction": "min", "observations": [{"value": [0.4059443771839142], "step": 19}]}}}, "score": 0.8461538553237915, "best_step": 19, "status": "COMPLETED", "message": null}